nasdaq_stock/__init__.py
nasdaq_stock/nasdaq_stock.py
nasdaq_stock-0.0.5.dist-info/LICENSE
nasdaq_stock-0.0.5.dist-info/METADATA
nasdaq_stock-0.0.5.dist-info/WHEEL
nasdaq_stock-0.0.5.dist-info/top_level.txt
nasdaq_stock-0.0.5.dist-info/RECORD
