Metadata-Version: 2.1
Name: nasdaq-stock
Version: 0.0.5
Summary: nasdaq stock retriever
Home-page: https://github.com/georgejs/nasdaq_stock
Download-URL: https://github.com/georgejs/nasdaq_stock/archive/0.0.5.tar.gz
Author: George Shen
Author-email: georgejs.arch@gmail.com
Keywords: stock,nasdaq,stock retriever,nasdaq stock
License-File: LICENSE
Requires-Dist: lxml
